{
  "productId": "333936177",
  "identifiers": {
    "internetNumber": "333936177",
    "modelNumber": "",
    "storeSkuNumber": "333936177"
  },
  "brand": {
    "name": "Husky",
    "logoUrl": "images/brands/husky.svg"
  },
  "title": "Heavy Duty 61 in. W x 23 in. D 15-Drawer Matte Gray Mobile Workbench Cabinet with Solid Wood Top",
  "shortDescription": "Heavy Duty 61 in. W x 23 in. D 15-Drawer Matte Gray Mobile Workbench Cabinet with Solid Wood Top",
  "longDescription": "Heavy Duty 61 in. W x 23 in. D 15-Drawer Matte Gray Mobile Workbench Cabinet with Solid Wood Top",
  "pricing": {
    "currentPrice": 898.0,
    "currency": "USD"
  },
  "rating": {
    "average": 4.3396,
    "count": 53
  },
  "media": {
    "primaryImage": "/products/333936177/matte-gray-husky-mobile-workbenches-h61mwc15hdgry-tl-64_100.jpg",
    "images": [
      {
        "url": "/products/333936177/matte-gray-husky-mobile-workbenches-h61mwc15hdgry-tl-64_100.jpg",
        "altText": "Heavy Duty 61 in. W x 23 in. D 15-Drawer Matte Gray Mobile Workbench Cabinet with Solid Wood Top",
        "type": "primary"
      }
    ]
  },
  "availability": {
    "inStock": true,
    "availableForPickup": true,
    "availableForDelivery": true
  },
  "badges": [],
  "specifications": {},
  "shipping": {
    "freeShipping": true
  },
  "version": "1.0",
  "lastUpdated": "2025-12-31T22:30:04.533307"
}