{
  "productId": "314160723",
  "identifiers": {
    "internetNumber": "314160723",
    "modelNumber": "",
    "storeSkuNumber": "314160723"
  },
  "brand": {
    "name": "Ejoy",
    "logoUrl": "images/brands/ejoy.svg"
  },
  "title": "20 in. H x 20 in. W GorgeousHome Artificial Boxwood Hedge Greenery Panels, DarkGreen (12-pc)",
  "shortDescription": "20 in. H x 20 in. W GorgeousHome Artificial Boxwood Hedge Greenery Panels, DarkGreen (12-pc)",
  "longDescription": "20 in. H x 20 in. W GorgeousHome Artificial Boxwood Hedge Greenery Panels, DarkGreen (12-pc)",
  "pricing": {
    "currentPrice": 63.34,
    "currency": "USD"
  },
  "rating": {
    "average": 4.6981,
    "count": 53
  },
  "media": {
    "primaryImage": "/products/314160723/ejoy-artificial-hedges-darkgreen-12pc-64_100.jpg",
    "images": [
      {
        "url": "/products/314160723/ejoy-artificial-hedges-darkgreen-12pc-64_100.jpg",
        "altText": "20 in. H x 20 in. W GorgeousHome Artificial Boxwood Hedge Greenery Panels, DarkGreen (12-pc)",
        "type": "primary"
      }
    ]
  },
  "availability": {
    "inStock": true,
    "availableForPickup": true,
    "availableForDelivery": true
  },
  "badges": [],
  "specifications": {},
  "shipping": {
    "freeShipping": true
  },
  "version": "1.0",
  "lastUpdated": "2026-01-08T16:53:19.920538",
  "plpTileType": "icon"
}